why not luaJIT?
	1G mem limit in 64bit environment
    need FFI
principles
	try not to change lua's native behavior
	主要优化可读性和性能的取舍处
bytecode optimization
	bytecode research
	bytecode loader/analyzer
	optimization
		common compiler optimization
		auto local(Common Subexpression Elimination)
		simple function inline
		constant inline
parrallel gc
	gc research
parrallel vm execution
	vm execution research
    哪些字节码执行过程中可能发生函数调用？
        各种元方法
        ADD     __add
        GETTABLE    __index
        SETTABLE    __newindex
some thing like SIMD?
	eg.
		multiple get table: A.B.C
		accumulator: A*B+C

LOADNIL优化
	lua解释器的原则是：函数开始到不是loadnil为止间的loadnil指令可以被省掉
	每个local其实初始化都是nil，所以可能会执行额外的loadnil
	>local a,b,c,d,e = nil,nil,0
	; function [0] definition (level 1)
	; 0 upvalues, 0 params, 5 stacks
	.function 0 0 2 5
	.local "a" ; 0
	.local "b" ; 1
	.local "c" ; 2
	.local "d" ; 3
	.local "e" ; 4
	.const 0 ; 0
	[1] loadk 2 0 ; 0
	[2] loadnil 3 4			-- 可以被优化掉
	[3] return 0 1
	; end of function
	
constant folding
	lua解释器会做简单的constant folding，只处理数值和布尔类型的一元和二元运算（负加减乘除余幂），字符串不会
	当解释器解析表达式的时候，按运算优先级判断，如果当前的运算是常数值就会在编译期求值，否则不会，比如
	a = 4+7+b会优化为a = 11+b
	a = b+4*7会优化为a = b+28
	而
	a = b+4+7则不会优化
	但如果写成
	a = b+(4+7)就会优化为a = b+11
	
	>local a = 4 + 7 + b; a = b + 4 * 7; a = b + 4 + 7
	; function [0] definition (level 1)
	; 0 upvalues, 0 params, 2 stacks
	.function 0 0 2 2
	.local "a" ; 0
	.const "b" ; 0
	.const 11 ; 1
	.const 28 ; 2
	.const 4 ; 3
	.const 7 ; 4
	[1] getglobal 0 0 ; b
	[2] add 0 257 0 ; 11 (a = 11 + b)
	[3] getglobal 1 0 ; b
	[4] add 0 1 258 ; 28 (a = b + 28)
	[5] getglobal 1 0 ; b
	[6] add 1 1 259 ; 4 (loc1 = b + 4)		-- 6、7可以优化为一条语句
	[7] add 0 1 260 ; 7 (a = loc1 + 7)
	[8] return 0 1
	; end of function
	
	字符串、除0，不会被优化，不过这种情况实际中比较少见
	>local a = 1 / 0; local b = 1 + "1"		-- 可以优化为local a = NaN; local b = 2
	; function [0] definition (level 1)
	; 0 upvalues, 0 params, 2 stacks
	.function 0 0 2 2
	.local "a" ; 0
	.local "b" ; 1
	.const 1 ; 0
	.const 0 ; 1
	.const "1" ; 2
	[1] div 0 256 257 ; 1 0
	[2] add 1 256 258 ; 1 "1"
	[3] return 0 1
	; end of function
	
	下面这几种目前也是没有constant folding的，不过实际情况也少见
	local a = #"hello"
	local b = "hello".."world"
	
求字符串长度的误区
	其实字符串长度可以用#求值，比string.len快5倍……

加执行参数
	chunk_spy [-fhv] lc_file
    f 是否进行流程分析
	h 是否显示文件头
    q 安静模式，不显示函数信息
    s 是否显示摘要信息
	v 是否显示描述字节码的冗余信息
	
会产生函数调用的字节码
    CALL
    TAILCALL
    ADD
    SUB
    MUL
    DIV
    MOD
    POW
    UNM
    CONCAT
    LEN
    EQ
    LT
    INDEX
    NEWINDEX
    元方法可能会是一个函数
    如果这个函数会修改外部的数据，那么在block内做local opt的时候需要非常注意

code block & flow analyzer
    通常会修改PC的是block的开始或结束
    以下指令必然是block的结尾
        JMP
        RETURN
        FORLOOP
        TFORLOOP
        TAILCALL
    作为数值for循环的开始语句，必然是block的开始
        FORPREP
    逻辑运算符虽然会修改PC，不过一定会跟随JMP，说明此block可能有2个后继，所以不作为结束
        EQ
        LT
        LE
        TEST
        TESTSET
    还有个特殊的例子，根据参数C，是指令中的立即数，来决定是否会跳转，所以需要判断一下C的值才决定是否是结束
        LOADBOOL
    所有移动到的PC值都会做为block的开始
    分析生成code的前驱和后继
        用于做死代码消除
        需要处理JMP, RETURN等语义

显示
    可读性比较好的字节码显示
    能够直接打印局部变量
        注意，函数参数的作用域是从第0条字节码开始的，而不是第i1条
    format开始时生成整个函数的栈帧，这里的栈帧主要是用来区分local变量和临时变量

code edit
    delete, insert
    不破坏block结构
    还有问题，需要各种调试
    实现modify(和先delete再insert不同，只处理一次)
    更新变量作用域
    更新跳转的偏移
        因为跳转会产生code block，所以在block中增删代码理论上不会破坏跳转的结构，只会改变地址
    保证每次修改后函数都是完整的(可以format)
    常量表在最后统一更新一次，清理掉未使用的

local optimization
    constant folding
        需要保证所有重定义算术运算元方法满足交换律，即
        V+K = K+V
        这样才能让形如
        K1+V+K2
        的代码优化为
        K1+K2+V
        所以提供一个-c的选项来决定是否要打开constant folding优化
TODO:
写完constant folding之后重构一次代码
    类型定义
    杂项功能
    优化
    输出打印
    constant propagation

